CHANGES.txt
LICENSE.txt
MANIFEST.in
README.txt
setup.py
IWD/__init__.py
IWD/iwd.py
IWD/miwd.py
IWD.egg-info/PKG-INFO
IWD.egg-info/SOURCES.txt
IWD.egg-info/dependency_links.txt
IWD.egg-info/requires.txt
IWD.egg-info/top_level.txt
IWD/test/__init__.py