Metadata-Version: 1.0
Name: IWD
Version: 0.1.0
Summary: Intelligent Water Drops Algorithm for TSP.
Home-page: http://pypi.python.org/pypi/IWD/
Author: Duvvuri Surya Rahul
Author-email: dsrahul@outlook.com
License: LICENSE.txt
Platform: UNKNOWN
